pybundler/__init__.py
pybundler/__main__.py
pybundler/cli.py
pybundler-0.4.0.dist-info/LICENSE
pybundler-0.4.0.dist-info/METADATA
pybundler-0.4.0.dist-info/WHEEL
pybundler-0.4.0.dist-info/entry_points.txt
pybundler-0.4.0.dist-info/top_level.txt
pybundler-0.4.0.dist-info/RECORD
