Metadata-Version: 2.1
Name: pybundler
Version: 0.4.0
Summary: Create or manage a python app or package
Home-page: https://github.com/dany2691/pybundler
Author: Daniel Omar Vergara Pérez
Author-email: daniel.omar.vergara@gmail.com
License: MIT
Platform: UNKNOWN
Classifier: License :: OSI Approved :: MIT License
Classifier: Programming Language :: Python :: 3.5
Classifier: Programming Language :: Python :: 3.6
Classifier: Programming Language :: Python :: 3.7
Classifier: Programming Language :: Python :: Implementation :: CPython
Classifier: Programming Language :: Python :: Implementation :: PyPy
Requires-Dist: click
Requires-Dist: colored
Requires-Dist: pypkg-generator
Requires-Dist: pipenv
Requires-Dist: twine
